{
  "ProjectFilePath": "c:\\Users\\andre\\Downloads\\ProjectServerConnector\\ProjectServerConnector\\Cireson.Connectors.ProjectConnector\\Cireson.Connectors.Project.Adapter\\Microsoft.EnterpriseManagement.ServiceManager.ProjectServer.Adapter.csproj",
  "TargetFramework": "v4.5",
  "TagHelpers": [],
  "Configuration": {
    "ConfigurationName": "UnsupportedRazor",
    "LanguageVersion": "1.0",
    "Extensions": [
      {
        "ExtensionName": "UnsupportedRazorExtension"
      }
    ]
  }
}